{
	"info": {
		"_postman_id": "c1f77d33-4f9a-41e9-a417-640a233fa0bd",
		"name": "Payment Service Manual Testing",
		"schema": "https://schema.getpostman.com/json/collection/v2.1.0/collection.json"
	},
	"item": [
		{
			"name": "Direct Test - Process Payment",
			"request": {
				"method": "POST",
				"header": [
					{
						"key": "Content-Type",
						"value": "application/json",
						"type": "text"
					}
				],
				"body": {
					"mode": "raw",
					"raw": "{\n  \"orderId\": \"3fa85f64-5717-4562-b3fc-2c963f66afa6\",\n  \"customerId\": \"d290f1ee-6c54-4b01-90e6-d701748f0851\",\n  \"totalPrice\": 250.00\n}"
				},
				"url": {
					"raw": "http://localhost:8086/api/payments/test",
					"protocol": "http",
					"host": [
						"localhost"
					],
					"port": "8086",
					"path": [
						"api",
						"payments",
						"test"
					]
				},
				"description": "Trigger the Payment Service logic directly via the custom REST Controller."
			},
			"response": []
		},
		{
			"name": "E2E - Step 1: Register User",
			"request": {
				"method": "POST",
				"header": [
					{
						"key": "Content-Type",
						"value": "application/json",
						"type": "text"
					}
				],
				"body": {
					"mode": "raw",
					"raw": "{\n  \"username\": \"johndoe\",\n  \"email\": \"john@example.com\",\n  \"password\": \"password123\"\n}"
				},
				"url": {
					"raw": "http://localhost:8080/api/auth/register",
					"protocol": "http",
					"host": [
						"localhost"
					],
					"port": "8080",
					"path": [
						"api",
						"auth",
						"register"
					]
				}
			},
			"response": []
		},
		{
			"name": "E2E - Step 2: Login User (Get Token)",
			"request": {
				"method": "POST",
				"header": [
					{
						"key": "Content-Type",
						"value": "application/json",
						"type": "text"
					}
				],
				"body": {
					"mode": "raw",
					"raw": "{\n  \"username\": \"johndoe\",\n  \"password\": \"password123\"\n}"
				},
				"url": {
					"raw": "http://localhost:8080/api/auth/login",
					"protocol": "http",
					"host": [
						"localhost"
					],
					"port": "8080",
					"path": [
						"api",
						"auth",
						"login"
					]
				}
			},
			"response": []
		},
		{
			"name": "E2E - Step 3: Place Order",
			"request": {
				"method": "POST",
				"header": [
					{
						"key": "Content-Type",
						"value": "application/json",
						"type": "text"
					},
					{
						"key": "X-User-Id",
						"value": "d290f1ee-6c54-4b01-90e6-d701748f0851",
						"type": "text"
					},
					{
						"key": "Authorization",
						"value": "Bearer <YOUR_JWT_TOKEN>",
						"type": "text"
					}
				],
				"body": {
					"mode": "raw",
					"raw": "{\n  \"items\": [\n    {\n      \"id\": \"e23db731-bfb8-4c91-949e-fb08e62c1619\",\n      \"quantity\": 1,\n      \"price\": 250.00,\n      \"subtotal\": 250.00\n    }\n  ]\n}"
				},
				"url": {
					"raw": "http://localhost:8080/api/orders",
					"protocol": "http",
					"host": [
						"localhost"
					],
					"port": "8080",
					"path": [
						"api",
						"orders"
					]
				}
			},
			"response": []
		},
		{
			"name": "E2E - Step 4: Check Order Status",
			"request": {
				"method": "GET",
				"header": [
					{
						"key": "Authorization",
						"value": "Bearer <YOUR_JWT_TOKEN>",
						"type": "text"
					}
				],
				"url": {
					"raw": "http://localhost:8080/api/orders/{{orderId}}",
					"protocol": "http",
					"host": [
						"localhost"
					],
					"port": "8080",
					"path": [
						"api",
						"orders",
						"{{orderId}}"
					]
				}
			},
			"response": []
		}
	]
}
